{
  "Baseline": [
    {
      "section": "Abstract",
      "question": "What year is the WMT English-to-French translation task that the model was evaluated on?",
      "expected": "2014",
      "got": "2014.English-to-FrenchĠtask-specificallyearlierumbersusereval2014.```ĊOkay,thoroughly,throu",
      "correct": true,
      "input_len": 1545,
      "compressed_len": 1545,
      "retention_pct": 100.0,
      "prefill_time": 0.3765578269958496,
      "compress_time": 0.0,
      "decode_time": 1.5409080982208252,
      "total_time": 1.917471170425415,
      "peak_mem_gb": 16.265361785888672
    },
    {
      "section": "Introduction",
      "question": "The Transformer avoids recurrence by using what mechanism to capture global dependencies?",
      "expected": "attention mechanisms|Attention mechanisms|attention",
      "got": "AttentionĠmechanismsĠlikeĠattentionĠmechanismĊOkay,attention:AttentionĠmechanism,attentionĠmechanism,attentionĠmechanism",
      "correct": true,
      "input_len": 1539,
      "compressed_len": 1539,
      "retention_pct": 100.0,
      "prefill_time": 0.03386855125427246,
      "compress_time": 0.0,
      "decode_time": 1.3254919052124023,
      "total_time": 1.3593645095825195,
      "peak_mem_gb": 16.260037422180176
    },
    {
      "section": "Attention",
      "question": "In the Scaled Dot-Product Attention formula, what do we divide the dot products by?",
      "expected": "sqrt(dk)|sqrt(d",
      "got": "Inthequery(QKewebĠdividedthedotproductsoforsimproceedingeneral,weĠdividedthequery,weĠdividebydiv",
      "correct": false,
      "input_len": 1542,
      "compressed_len": 1542,
      "retention_pct": 100.0,
      "prefill_time": 0.03075551986694336,
      "compress_time": 0.0,
      "decode_time": 1.224902629852295,
      "total_time": 1.2556614875793457,
      "peak_mem_gb": 16.263332843780518
    },
    {
      "section": "Positional Encoding",
      "question": "Positional encodings are added to the input embeddings at the what of the encoder and decoder stacks?",
      "expected": "bottoms|bottom|encoder and decoder",
      "got": "PositionalwayĠbelowĠtheĠbottomĠofĠtheĠbottomĠofĠtheĠencoderĠandĠthenumberserlatchestopinĠpos=Theditspositionalized",
      "correct": true,
      "input_len": 1545,
      "compressed_len": 1545,
      "retention_pct": 100.0,
      "prefill_time": 0.0305788516998291,
      "compress_time": 0.0,
      "decode_time": 1.253453254699707,
      "total_time": 1.2840349674224854,
      "peak_mem_gb": 16.265148639678955
    },
    {
      "section": "Training",
      "question": "What is the label smoothing value eps_ls used during training?",
      "expected": "0.1",
      "got": "0.1.1.1.1.1.1.1.1.**</answithebasically,eps_ls=>Ċ",
      "correct": true,
      "input_len": 1536,
      "compressed_len": 1536,
      "retention_pct": 100.0,
      "prefill_time": 0.042684078216552734,
      "compress_time": 0.0,
      "decode_time": 1.6136856079101562,
      "total_time": 1.6563725471496582,
      "peak_mem_gb": 16.257502555847168
    },
    {
      "section": "Results",
      "question": "How long did it take to train the big transformer model on 8 P100 GPUs?",
      "expected": "3.5 days|3.5days|3.5",
      "got": "Ittook3.5,itisĠtrainedĠforĠtheĠbigĠtransformerĠbigĠtransformerĠbigĠtransformerĠmodelsĊOkay,trainingtimeisAllright?Answer",
      "correct": true,
      "input_len": 1542,
      "compressed_len": 1542,
      "retention_pct": 100.0,
      "prefill_time": 0.043718814849853516,
      "compress_time": 0.0,
      "decode_time": 1.5784027576446533,
      "total_time": 1.6221256256103516,
      "peak_mem_gb": 16.263332843780518
    }
  ],
  "SnapKV-128": [
    {
      "section": "Abstract",
      "question": "What year is the WMT English-to-French translation task that the model was evaluated on?",
      "expected": "2014",
      "got": "2014ĊĊOkay,ĠsoĠIĠneedĠtoĠfigureĠoutĠtheĠyearĠofĠtheĠWMTĠEnglish-to-FrenchĠtranslationĠtaskĠthatĠtheĠmodelĠwasĠevaluatedĠ",
      "correct": true,
      "input_len": 1545,
      "compressed_len": 128,
      "retention_pct": 8.3,
      "prefill_time": 0.043183088302612305,
      "compress_time": 0.20837950706481934,
      "decode_time": 1.138352632522583,
      "total_time": 1.40081787109375,
      "peak_mem_gb": 16.038143634796143
    },
    {
      "section": "Introduction",
      "question": "The Transformer avoids recurrence by using what mechanism to capture global dependencies?",
      "expected": "attention mechanisms|Attention mechanisms|attention",
      "got": "AttentionĠmechanisms.ĊĊOkay,ĠsoĠI'mĠtryingĠtoĠunderstandĠhowĠTheĠTransformerĠavoidsĠrecurrenceĠbyĠusingĠaĠmechanismĠtoĠc",
      "correct": true,
      "input_len": 1539,
      "compressed_len": 128,
      "retention_pct": 8.3,
      "prefill_time": 0.03941035270690918,
      "compress_time": 0.03334379196166992,
      "decode_time": 1.2753620147705078,
      "total_time": 1.427293062210083,
      "peak_mem_gb": 16.03515338897705
    },
    {
      "section": "Attention",
      "question": "In the Scaled Dot-Product Attention formula, what do we divide the dot products by?",
      "expected": "sqrt(dk)|sqrt(d",
      "got": "IntheScaledDot-ProductAttention,wecomputedthedotproductsofthequerywithallkeys,thenweĠdividedeachbyâĪļ(d_k",
      "correct": false,
      "input_len": 1542,
      "compressed_len": 128,
      "retention_pct": 8.3,
      "prefill_time": 0.04406905174255371,
      "compress_time": 0.11266016960144043,
      "decode_time": 1.3054955005645752,
      "total_time": 1.4672796726226807,
      "peak_mem_gb": 16.03112030029297
    },
    {
      "section": "Positional Encoding",
      "question": "Positional encodings are added to the input embeddings at the what of the encoder and decoder stacks?",
      "expected": "bottoms|bottom|encoder and decoder",
      "got": "Positionalencodingsareaddedtotheinputembeddingsatthewhatoftheencoderanddecoderstacks.ĊĊOkay,ĠsoĠI'mĠtryingĠtoĠunderstand",
      "correct": false,
      "input_len": 1545,
      "compressed_len": 128,
      "retention_pct": 8.3,
      "prefill_time": 0.03929257392883301,
      "compress_time": 0.033368587493896484,
      "decode_time": 1.029390811920166,
      "total_time": 1.1801352500915527,
      "peak_mem_gb": 16.035358905792236
    },
    {
      "section": "Training",
      "question": "What is the label smoothing value eps_ls used during training?",
      "expected": "0.1",
      "got": "0.1ĊĊOkay,ĠsoĠIĠneedĠtoĠfigureĠoutĠwhatĠtheĠlabelĠsmoothingĠvalueĠeps_lsĠisĠusedĠduringĠtraining.ĠI'mĠlookingĠthroughĠth",
      "correct": true,
      "input_len": 1536,
      "compressed_len": 128,
      "retention_pct": 8.3,
      "prefill_time": 0.028059005737304688,
      "compress_time": 0.039215803146362305,
      "decode_time": 0.9242806434631348,
      "total_time": 1.065201997756958,
      "peak_mem_gb": 16.031010627746582
    },
    {
      "section": "Results",
      "question": "How long did it take to train the big transformer model on 8 P100 GPUs?",
      "expected": "3.5 days|3.5days|3.5",
      "got": "Ittook3.5dayson8P100GPUs.ĊĊOkay,ĠsoĠIĠneedĠtoĠfigureĠoutĠhowĠlongĠitĠtookĠtoĠtrainĠtheĠbigĠtransformer",
      "correct": true,
      "input_len": 1542,
      "compressed_len": 128,
      "retention_pct": 8.3,
      "prefill_time": 0.03057551383972168,
      "compress_time": 0.04201340675354004,
      "decode_time": 0.9237878322601318,
      "total_time": 1.0751214027404785,
      "peak_mem_gb": 16.035018920898438
    }
  ],
  "SnapKV-256": [
    {
      "section": "Abstract",
      "question": "What year is the WMT English-to-French translation task that the model was evaluated on?",
      "expected": "2014",
      "got": "2014ĊĊOkay,ĠsoĠIĠneedĠtoĠfigureĠoutĠtheĠyearĠwhenĠtheĠWMTĠEnglish-to-FrenchĠtranslationĠtaskĠwasĠevaluated.ĠTheĠuserĠpro",
      "correct": true,
      "input_len": 1545,
      "compressed_len": 256,
      "retention_pct": 16.6,
      "prefill_time": 0.03064250946044922,
      "compress_time": 0.04184579849243164,
      "decode_time": 0.9152836799621582,
      "total_time": 1.0651650428771973,
      "peak_mem_gb": 15.996893405914307
    },
    {
      "section": "Introduction",
      "question": "The Transformer avoids recurrence by using what mechanism to capture global dependencies?",
      "expected": "attention mechanisms|Attention mechanisms|attention",
      "got": "AttentionĠmechanisms.ĊĊOkay,ĠsoĠI'mĠtryingĠtoĠunderstandĠhowĠtheĠTransformerĠavoidsĠrecurrenceĠbyĠusingĠaĠmechanismĠtoĠc",
      "correct": true,
      "input_len": 1539,
      "compressed_len": 256,
      "retention_pct": 16.6,
      "prefill_time": 0.03052544593811035,
      "compress_time": 0.04175567626953125,
      "decode_time": 0.9170589447021484,
      "total_time": 1.0654752254486084,
      "peak_mem_gb": 15.99409008026123
    },
    {
      "section": "Attention",
      "question": "In the Scaled Dot-Product Attention formula, what do we divide the dot products by?",
      "expected": "sqrt(dk)|sqrt(d",
      "got": "IntheScaledDot-ProductAttention,wecomputethedotproductsofthequerywithallkeys,divideeachbysqrt(dk),",
      "correct": true,
      "input_len": 1542,
      "compressed_len": 256,
      "retention_pct": 16.6,
      "prefill_time": 0.03065204620361328,
      "compress_time": 0.04182028770446777,
      "decode_time": 0.9139361381530762,
      "total_time": 1.0629756450653076,
      "peak_mem_gb": 15.994117259979248
    },
    {
      "section": "Positional Encoding",
      "question": "Positional encodings are added to the input embeddings at the what of the encoder and decoder stacks?",
      "expected": "bottoms|bottom|encoder and decoder",
      "got": "Positionalencodingsareaddedtotheinputembeddingsatthewhatoftheencoderanddecoderstacks.ĊĊOkay,ĠsoĠI'mĠtryingĠtoĠunderstand",
      "correct": false,
      "input_len": 1545,
      "compressed_len": 256,
      "retention_pct": 16.6,
      "prefill_time": 0.030636072158813477,
      "compress_time": 0.0417938232421875,
      "decode_time": 0.9187624454498291,
      "total_time": 1.0679395198822021,
      "peak_mem_gb": 15.99592638015747
    },
    {
      "section": "Training",
      "question": "What is the label smoothing value eps_ls used during training?",
      "expected": "0.1",
      "got": "0.1ĊĊOkay,ĠsoĠIĠneedĠtoĠfigureĠoutĠwhatĠtheĠlabelĠsmoothingĠvalueĠeps_lsĠisĠusedĠduringĠtraining.ĠI'mĠlookingĠthroughĠth",
      "correct": true,
      "input_len": 1536,
      "compressed_len": 256,
      "retention_pct": 16.7,
      "prefill_time": 0.02822256088256836,
      "compress_time": 0.03868603706359863,
      "decode_time": 0.9143168926239014,
      "total_time": 1.0529747009277344,
      "peak_mem_gb": 16.0023832321167
    },
    {
      "section": "Results",
      "question": "How long did it take to train the big transformer model on 8 P100 GPUs?",
      "expected": "3.5 days|3.5days|3.5",
      "got": "Ittook3.5dayson8P100GPUs.ĊĊOkay,ĠsoĠI'mĠtryingĠtoĠfigureĠoutĠhowĠlongĠitĠtookĠtoĠtrainĠtheĠbig",
      "correct": true,
      "input_len": 1542,
      "compressed_len": 256,
      "retention_pct": 16.6,
      "prefill_time": 0.030527353286743164,
      "compress_time": 0.04190182685852051,
      "decode_time": 0.9150476455688477,
      "total_time": 1.0625770092010498,
      "peak_mem_gb": 15.995425701141357
    }
  ],
  "SnapKV-512": [
    {
      "section": "Abstract",
      "question": "What year is the WMT English-to-French translation task that the model was evaluated on?",
      "expected": "2014",
      "got": "2014ĊĊOkay,ĠsoĠIĠneedĠtoĠfigureĠoutĠtheĠyearĠwhenĠtheĠWMTĠEnglish-to-FrenchĠtranslationĠtaskĠwasĠevaluated.ĠTheĠuserĠpro",
      "correct": true,
      "input_len": 1545,
      "compressed_len": 512,
      "retention_pct": 33.1,
      "prefill_time": 0.03066229820251465,
      "compress_time": 0.04208564758300781,
      "decode_time": 0.9001460075378418,
      "total_time": 1.047917127609253,
      "peak_mem_gb": 15.9129638671875
    },
    {
      "section": "Introduction",
      "question": "The Transformer avoids recurrence by using what mechanism to capture global dependencies?",
      "expected": "attention mechanisms|Attention mechanisms|attention",
      "got": "AttentionĠmechanisms.ĊĊOkay,ĠsoĠI'mĠtryingĠtoĠunderstandĠhowĠtheĠTransformerĠavoidsĠrecurrenceĠbyĠusingĠaĠmechanismĠtoĠc",
      "correct": true,
      "input_len": 1539,
      "compressed_len": 512,
      "retention_pct": 33.3,
      "prefill_time": 0.03057384490966797,
      "compress_time": 0.04180455207824707,
      "decode_time": 0.9020960330963135,
      "total_time": 1.0495927333831787,
      "peak_mem_gb": 15.90848684310913
    },
    {
      "section": "Attention",
      "question": "In the Scaled Dot-Product Attention formula, what do we divide the dot products by?",
      "expected": "sqrt(dk)|sqrt(d",
      "got": "WeĠdividedĠeachĠdotĠproductĠbyĠsqrt(dk),ĠwhereĠdkĠisĠtheĠdimensionĠofĠtheĠkeys.ĊĊOkay,ĠsoĠI'mĠtryingĠtoĠunderstandĠtheĠs",
      "correct": true,
      "input_len": 1542,
      "compressed_len": 512,
      "retention_pct": 33.2,
      "prefill_time": 0.030659914016723633,
      "compress_time": 0.0417935848236084,
      "decode_time": 0.9044589996337891,
      "total_time": 1.0526392459869385,
      "peak_mem_gb": 15.912744522094727
    },
    {
      "section": "Positional Encoding",
      "question": "Positional encodings are added to the input embeddings at the what of the encoder and decoder stacks?",
      "expected": "bottoms|bottom|encoder and decoder",
      "got": "Positionalencodingsareaddedtotheinputembeddingsatthewhatoftheencoderanddecoderstacks.ĊĊOkay,ĠsoĠI'mĠtryingĠtoĠunderstand",
      "correct": false,
      "input_len": 1545,
      "compressed_len": 512,
      "retention_pct": 33.1,
      "prefill_time": 0.030677080154418945,
      "compress_time": 0.04209089279174805,
      "decode_time": 0.9005277156829834,
      "total_time": 1.0486054420471191,
      "peak_mem_gb": 15.912210464477539
    },
    {
      "section": "Training",
      "question": "What is the label smoothing value eps_ls used during training?",
      "expected": "0.1",
      "got": "0.1ĊĊOkay,ĠsoĠIĠneedĠtoĠfigureĠoutĠwhatĠtheĠlabelĠsmoothingĠvalueĠeps_lsĠisĠusedĠduringĠtraining.ĠI'mĠlookingĠthroughĠth",
      "correct": true,
      "input_len": 1536,
      "compressed_len": 512,
      "retention_pct": 33.3,
      "prefill_time": 0.02815699577331543,
      "compress_time": 0.03878045082092285,
      "decode_time": 0.8891122341156006,
      "total_time": 1.029151201248169,
      "peak_mem_gb": 15.906647682189941
    },
    {
      "section": "Results",
      "question": "How long did it take to train the big transformer model on 8 P100 GPUs?",
      "expected": "3.5 days|3.5days|3.5",
      "got": "Ittook3.5dayson8P100GPUs.ĊĊOkay,ĠsoĠI'mĠtryingĠtoĠfigureĠoutĠhowĠlongĠitĠtookĠtoĠtrainĠtheĠbig",
      "correct": true,
      "input_len": 1542,
      "compressed_len": 512,
      "retention_pct": 33.2,
      "prefill_time": 0.030969619750976562,
      "compress_time": 0.04184746742248535,
      "decode_time": 0.8999133110046387,
      "total_time": 1.0466012954711914,
      "peak_mem_gb": 15.912836074829102
    }
  ],
  "SnapKV-1024": [
    {
      "section": "Abstract",
      "question": "What year is the WMT English-to-French translation task that the model was evaluated on?",
      "expected": "2014",
      "got": "2014ĊĊOkay,ĠsoĠIĠneedĠtoĠfigureĠoutĠtheĠyearĠwhenĠtheĠWMTĠEnglish-to-FrenchĠtranslationĠtaskĠwasĠevaluated.ĠTheĠtextĠpro",
      "correct": true,
      "input_len": 1545,
      "compressed_len": 1024,
      "retention_pct": 66.3,
      "prefill_time": 0.03062725067138672,
      "compress_time": 0.04191732406616211,
      "decode_time": 0.8612704277038574,
      "total_time": 1.0118935108184814,
      "peak_mem_gb": 15.917210578918457
    },
    {
      "section": "Introduction",
      "question": "The Transformer avoids recurrence by using what mechanism to capture global dependencies?",
      "expected": "attention mechanisms|Attention mechanisms|attention",
      "got": "AttentionĠmechanisms.ĊĊOkay,ĠsoĠI'mĠtryingĠtoĠunderstandĠhowĠtheĠTransformerĠavoidsĠrecurrenceĠbyĠusingĠaĠmechanismĠtoĠc",
      "correct": true,
      "input_len": 1539,
      "compressed_len": 1024,
      "retention_pct": 66.5,
      "prefill_time": 0.030835628509521484,
      "compress_time": 0.04193592071533203,
      "decode_time": 0.8565013408660889,
      "total_time": 1.0034348964691162,
      "peak_mem_gb": 15.91174030303955
    },
    {
      "section": "Attention",
      "question": "In the Scaled Dot-Product Attention formula, what do we divide the dot products by?",
      "expected": "sqrt(dk)|sqrt(d",
      "got": "IntheScaledDot-ProductAttention,wecomputedthedotproductsofthequerywithallkeys,thenweĠdividedeachbyâĪļ(d_k",
      "correct": false,
      "input_len": 1542,
      "compressed_len": 1024,
      "retention_pct": 66.4,
      "prefill_time": 0.03086543083190918,
      "compress_time": 0.041835784912109375,
      "decode_time": 0.8494434356689453,
      "total_time": 0.9959447383880615,
      "peak_mem_gb": 15.915505409240723
    },
    {
      "section": "Positional Encoding",
      "question": "Positional encodings are added to the input embeddings at the what of the encoder and decoder stacks?",
      "expected": "bottoms|bottom|encoder and decoder",
      "got": "Positionalencodingsareaddedtotheinputembeddingsatthewhatoftheencoderanddecoderstacks.ĊĊOkay,ĠsoĠI'mĠtryingĠtoĠunderstand",
      "correct": false,
      "input_len": 1545,
      "compressed_len": 1024,
      "retention_pct": 66.3,
      "prefill_time": 0.030890226364135742,
      "compress_time": 0.04223823547363281,
      "decode_time": 0.8498075008392334,
      "total_time": 0.9971106052398682,
      "peak_mem_gb": 15.916388511657715
    },
    {
      "section": "Training",
      "question": "What is the label smoothing value eps_ls used during training?",
      "expected": "0.1",
      "got": "0.1ĊĊOkay,ĠsoĠIĠneedĠtoĠfigureĠoutĠwhatĠtheĠlabelĠsmoothingĠvalueĠeps_lsĠisĠusedĠduringĠtraining.ĠI'mĠlookingĠthroughĠth",
      "correct": true,
      "input_len": 1536,
      "compressed_len": 1024,
      "retention_pct": 66.7,
      "prefill_time": 0.028414487838745117,
      "compress_time": 0.038661956787109375,
      "decode_time": 0.8596663475036621,
      "total_time": 0.9968416690826416,
      "peak_mem_gb": 15.934256553649902
    },
    {
      "section": "Results",
      "question": "How long did it take to train the big transformer model on 8 P100 GPUs?",
      "expected": "3.5 days|3.5days|3.5",
      "got": "Ittook3.5dayson8P100GPUs.ĊĊOkay,ĠsoĠIĠneedĠtoĠfigureĠoutĠhowĠlongĠitĠtookĠtoĠtrainĠtheĠbigĠtransformer",
      "correct": true,
      "input_len": 1542,
      "compressed_len": 1024,
      "retention_pct": 66.4,
      "prefill_time": 0.030669450759887695,
      "compress_time": 0.042084455490112305,
      "decode_time": 0.8493506908416748,
      "total_time": 0.9968447685241699,
      "peak_mem_gb": 15.915505409240723
    }
  ],
  "Random-256": [
    {
      "section": "Abstract",
      "question": "What year is the WMT English-to-French translation task that the model was evaluated on?",
      "expected": "2014",
      "got": "WhatyearistĠWMTEEnglishĠBasEvalon:AnswerYearistEvalononAnswerYearistYearistYearistYearYearYearAnswerYearAnswerYear",
      "correct": false,
      "input_len": 1545,
      "compressed_len": 256,
      "retention_pct": 16.6,
      "prefill_time": 0.030879974365234375,
      "compress_time": 0.12856030464172363,
      "decode_time": 0.927391529083252,
      "total_time": 1.0868415832519531,
      "peak_mem_gb": 15.998674869537354
    },
    {
      "section": "Introduction",
      "question": "The Transformer avoids recurrence by using what mechanism to capture global dependencies?",
      "expected": "attention mechanisms|Attention mechanisms|attention",
      "got": "TheTransformeravoidsrecemt[ThePIs]WHIsThePIs]WHIsThePIs,ThePIs,",
      "correct": false,
      "input_len": 1539,
      "compressed_len": 256,
      "retention_pct": 16.6,
      "prefill_time": 0.0306851863861084,
      "compress_time": 0.04578733444213867,
      "decode_time": 0.9087789058685303,
      "total_time": 1.0543768405914307,
      "peak_mem_gb": 15.994227409362793
    },
    {
      "section": "Attention",
      "question": "In the Scaled Dot-Product Attention formula, what do we divide the dot products by?",
      "expected": "sqrt(dk)|sqrt(d",
      "got": "InScaledDot-ProductFormula,whatdowediedth:Answer:InScaledDot-ProductFormula,whatdowed:Answer:InĠscaled",
      "correct": false,
      "input_len": 1542,
      "compressed_len": 256,
      "retention_pct": 16.6,
      "prefill_time": 0.030594348907470703,
      "compress_time": 0.046210527420043945,
      "decode_time": 0.9149749279022217,
      "total_time": 1.0608189105987549,
      "peak_mem_gb": 15.99647569656372
    },
    {
      "section": "Positional Encoding",
      "question": "Positional encodings are added to the input embeddings at the what of the encoder and decoder stacks?",
      "expected": "bottoms|bottom|encoder and decoder",
      "got": "PositionalencodingsareaddedtotheinputĠembeddingsatwhatofWhatWhatPositionAnswerPositionAnswerPositionAnswerAnswerAnswerAn",
      "correct": false,
      "input_len": 1545,
      "compressed_len": 256,
      "retention_pct": 16.6,
      "prefill_time": 0.030594587326049805,
      "compress_time": 0.04590106010437012,
      "decode_time": 0.9309382438659668,
      "total_time": 1.0759856700897217,
      "peak_mem_gb": 15.998674869537354
    },
    {
      "section": "Training",
      "question": "What is the label smoothing value eps_ls used during training?",
      "expected": "0.1",
      "got": "Labelsmeps_ls.UsedĠduringĠtraining.EPS_ls.UsedĠduringĠtraining.EPS_ls.UsedĠduringEPS_ls.eps_ls.eps_ls.",
      "correct": false,
      "input_len": 1536,
      "compressed_len": 256,
      "retention_pct": 16.7,
      "prefill_time": 0.028232097625732422,
      "compress_time": 0.04252290725708008,
      "decode_time": 0.9060029983520508,
      "total_time": 1.042898178100586,
      "peak_mem_gb": 15.9901762008667
    },
    {
      "section": "Results",
      "question": "How long did it take to train the big transformer model on 8 P100 GPUs?",
      "expected": "3.5 days|3.5days|3.5",
      "got": "300000stepstepĊAnswer:BiglongitottonetbiglongitAnswer:HowlongdiditAnswerlongAnswerbiglongAnswerAnswerAnswerAnswer",
      "correct": false,
      "input_len": 1542,
      "compressed_len": 256,
      "retention_pct": 16.6,
      "prefill_time": 0.030707836151123047,
      "compress_time": 0.046030521392822266,
      "decode_time": 0.9088764190673828,
      "total_time": 1.055673599243164,
      "peak_mem_gb": 15.993130207061768
    }
  ],
  "Random-512": [
    {
      "section": "Abstract",
      "question": "What year is the WMT English-to-French translation task that the model was evaluated on?",
      "expected": "2014",
      "got": "201.ĠBas.ĠModel.ĠThebasĠmodel.ĠThebasĠmodel.ĠThebasĠmodel.ĠThebasĠmodel.ĠThebasĠmodel.ĠThebasĠmodel.",
      "correct": false,
      "input_len": 1545,
      "compressed_len": 512,
      "retention_pct": 33.1,
      "prefill_time": 0.030661821365356445,
      "compress_time": 0.046135902404785156,
      "decode_time": 0.9002926349639893,
      "total_time": 1.045964002609253,
      "peak_mem_gb": 15.912210464477539
    },
    {
      "section": "Introduction",
      "question": "The Transformer avoids recurrence by using what mechanism to capture global dependencies?",
      "expected": "attention mechanisms|Attention mechanisms|attention",
      "got": "AnattentionĠmechanism.ĊQuestion:ĠTheĠmechanismĠusedĠtoĠcaptureĠglobalĠdependenciesĠisĠattention.ĊĊAnswer:ĠAnĠattentionĠm",
      "correct": true,
      "input_len": 1539,
      "compressed_len": 512,
      "retention_pct": 33.3,
      "prefill_time": 0.030604124069213867,
      "compress_time": 0.04624438285827637,
      "decode_time": 0.8936307430267334,
      "total_time": 1.0401997566223145,
      "peak_mem_gb": 15.90848684310913
    },
    {
      "section": "Attention",
      "question": "In the Scaled Dot-Product Attention formula, what do we divide the dot products by?",
      "expected": "sqrt(dk)|sqrt(d",
      "got": "Divtheduedscaled.Answer:Answer:Answer.Answer:Answer.Answer:Answer.Answer:Answer.Answer.Answer:Answer.Answer",
      "correct": false,
      "input_len": 1542,
      "compressed_len": 512,
      "retention_pct": 33.2,
      "prefill_time": 0.030670881271362305,
      "compress_time": 0.046053171157836914,
      "decode_time": 0.8925960063934326,
      "total_time": 1.039168357849121,
      "peak_mem_gb": 15.911088943481445
    },
    {
      "section": "Positional Encoding",
      "question": "Positional encodings are added to the input embeddings at the what of the encoder and decoder stacks?",
      "expected": "bottoms|bottom|encoder and decoder",
      "got": "Positionalencodingsareaddedtotheinputofthewitencod,1,PE,addedtotheencoderanddecoderstacks,what",
      "correct": false,
      "input_len": 1545,
      "compressed_len": 512,
      "retention_pct": 33.1,
      "prefill_time": 0.030796527862548828,
      "compress_time": 0.046163082122802734,
      "decode_time": 0.8914248943328857,
      "total_time": 1.0385181903839111,
      "peak_mem_gb": 15.912210464477539
    },
    {
      "section": "Training",
      "question": "What is the label smoothing value eps_ls used during training?",
      "expected": "0.1",
      "got": "WhatĠisĠtheĠlabelĠsmoothingĠvalueĠeps_ĠlsĠusedĠduringĠtraining.ĠTheĠlabelĠsmoothingĠvalueĠisĠ0.1,ĠwhichĠisĠtheĠvalueĠofĠ",
      "correct": true,
      "input_len": 1536,
      "compressed_len": 512,
      "retention_pct": 33.3,
      "prefill_time": 0.028280019760131836,
      "compress_time": 0.04257774353027344,
      "decode_time": 0.9285373687744141,
      "total_time": 1.0652697086334229,
      "peak_mem_gb": 15.906647682189941
    },
    {
      "section": "Results",
      "question": "How long did it take to train the big transformer model on 8 P100 GPUs?",
      "expected": "3.5 days|3.5days|3.5",
      "got": "ItTakedLongStepT[]StepStepStepStepStepStep[]Step[Step]Step[].Step[Step]Step).Step",
      "correct": false,
      "input_len": 1542,
      "compressed_len": 512,
      "retention_pct": 33.2,
      "prefill_time": 0.03073906898498535,
      "compress_time": 0.046024322509765625,
      "decode_time": 0.9034652709960938,
      "total_time": 1.049004316329956,
      "peak_mem_gb": 15.911088943481445
    }
  ],
  "KeepFirst-256": [
    {
      "section": "Abstract",
      "question": "What year is the WMT English-to-French translation task that the model was evaluated on?",
      "expected": "2014",
      "got": "2014ĊĊOkay,ĠsoĠIĠneedĠtoĠfigureĠoutĠtheĠyearĠwhenĠtheĠWMTĠEnglish-to-FrenchĠtranslationĠtaskĠwasĠevaluated.ĠTheĠtextĠpro",
      "correct": true,
      "input_len": 1545,
      "compressed_len": 256,
      "retention_pct": 16.6,
      "prefill_time": 0.030779361724853516,
      "compress_time": 0.005663156509399414,
      "decode_time": 0.9248902797698975,
      "total_time": 1.071690320968628,
      "peak_mem_gb": 15.995033740997314
    },
    {
      "section": "Introduction",
      "question": "The Transformer avoids recurrence by using what mechanism to capture global dependencies?",
      "expected": "attention mechanisms|Attention mechanisms|attention",
      "got": "AttentionĠmechanisms.ĊĊOkay,ĠsoĠI'mĠtryingĠtoĠunderstandĠhowĠTheĠTransformerĠavoidsĠrecurrenceĠbyĠusingĠaĠmechanismĠtoĠc",
      "correct": true,
      "input_len": 1539,
      "compressed_len": 256,
      "retention_pct": 16.6,
      "prefill_time": 0.030689001083374023,
      "compress_time": 0.005662202835083008,
      "decode_time": 0.9107122421264648,
      "total_time": 1.0554282665252686,
      "peak_mem_gb": 15.985861778259277
    },
    {
      "section": "Attention",
      "question": "In the Scaled Dot-Product Attention formula, what do we divide the dot products by?",
      "expected": "sqrt(dk)|sqrt(d",
      "got": "IntheScaledDot-ProductAttention,wecomputethedotproductsofthequerywithallkeys,divideeachbysqrt(dk),",
      "correct": true,
      "input_len": 1542,
      "compressed_len": 256,
      "retention_pct": 16.6,
      "prefill_time": 0.030701875686645508,
      "compress_time": 0.005693674087524414,
      "decode_time": 0.9224205017089844,
      "total_time": 1.066946029663086,
      "peak_mem_gb": 15.992233753204346
    },
    {
      "section": "Positional Encoding",
      "question": "Positional encodings are added to the input embeddings at the what of the encoder and decoder stacks?",
      "expected": "bottoms|bottom|encoder and decoder",
      "got": "Positionalencodingsareaddedtotheinputembeddingsatthewhatoftheencoderanddecoderstacks.ĊĊOkay,ĠsoĠI'mĠtryingĠtoĠunderstand",
      "correct": false,
      "input_len": 1545,
      "compressed_len": 256,
      "retention_pct": 16.6,
      "prefill_time": 0.030751943588256836,
      "compress_time": 0.005674123764038086,
      "decode_time": 0.927487850189209,
      "total_time": 1.0720982551574707,
      "peak_mem_gb": 15.992603778839111
    },
    {
      "section": "Training",
      "question": "What is the label smoothing value eps_ls used during training?",
      "expected": "0.1",
      "got": "0.1ĊĊOkay,ĠsoĠIĠneedĠtoĠfigureĠoutĠwhatĠtheĠlabelĠsmoothingĠvalueĠeps_lsĠisĠusedĠduringĠtraining.ĠLetĠmeĠreadĠthroughĠth",
      "correct": true,
      "input_len": 1536,
      "compressed_len": 256,
      "retention_pct": 16.7,
      "prefill_time": 0.028331279754638672,
      "compress_time": 0.005240917205810547,
      "decode_time": 0.901066780090332,
      "total_time": 1.0357816219329834,
      "peak_mem_gb": 15.9955472946167
    },
    {
      "section": "Results",
      "question": "How long did it take to train the big transformer model on 8 P100 GPUs?",
      "expected": "3.5 days|3.5days|3.5",
      "got": "Ittook3.5dayson8P100GPUs.ĊOkay,ĠsoĠIĠneedĠtoĠfigureĠoutĠhowĠlongĠitĠtookĠtoĠtrainĠtheĠbigĠtransformer",
      "correct": true,
      "input_len": 1542,
      "compressed_len": 256,
      "retention_pct": 16.6,
      "prefill_time": 0.030722379684448242,
      "compress_time": 0.0056803226470947266,
      "decode_time": 0.9093058109283447,
      "total_time": 1.0541191101074219,
      "peak_mem_gb": 15.98853349685669
    }
  ],
  "KeepFirst-512": [
    {
      "section": "Abstract",
      "question": "What year is the WMT English-to-French translation task that the model was evaluated on?",
      "expected": "2014",
      "got": "2014ĊĊOkay,ĠsoĠIĠneedĠtoĠfigureĠoutĠtheĠyearĠwhenĠtheĠWMTĠEnglish-to-FrenchĠtranslationĠtaskĠwasĠevaluated.ĠTheĠuserĠpro",
      "correct": true,
      "input_len": 1545,
      "compressed_len": 512,
      "retention_pct": 33.1,
      "prefill_time": 0.030768156051635742,
      "compress_time": 0.006466388702392578,
      "decode_time": 0.8894305229187012,
      "total_time": 1.0335209369659424,
      "peak_mem_gb": 15.912210464477539
    },
    {
      "section": "Introduction",
      "question": "The Transformer avoids recurrence by using what mechanism to capture global dependencies?",
      "expected": "attention mechanisms|Attention mechanisms|attention",
      "got": "AttentionĠmechanisms.ĊĊOkay,ĠsoĠI'mĠtryingĠtoĠunderstandĠhowĠtheĠTransformerĠavoidsĠrecurrenceĠbyĠusingĠaĠmechanismĠtoĠc",
      "correct": true,
      "input_len": 1539,
      "compressed_len": 512,
      "retention_pct": 33.3,
      "prefill_time": 0.03075242042541504,
      "compress_time": 0.005715131759643555,
      "decode_time": 0.8913357257843018,
      "total_time": 1.0363149642944336,
      "peak_mem_gb": 15.90848684310913
    },
    {
      "section": "Attention",
      "question": "In the Scaled Dot-Product Attention formula, what do we divide the dot products by?",
      "expected": "sqrt(dk)|sqrt(d",
      "got": "IntheScaledDot-ProductAttention,wecomputethedotproductsofthequerywithallkeys,divideeachbysqrt(dk),",
      "correct": true,
      "input_len": 1542,
      "compressed_len": 512,
      "retention_pct": 33.2,
      "prefill_time": 0.030753135681152344,
      "compress_time": 0.005670070648193359,
      "decode_time": 0.8922686576843262,
      "total_time": 1.0375196933746338,
      "peak_mem_gb": 15.911088943481445
    },
    {
      "section": "Positional Encoding",
      "question": "Positional encodings are added to the input embeddings at the what of the encoder and decoder stacks?",
      "expected": "bottoms|bottom|encoder and decoder",
      "got": "Positionalencodingsareaddedtotheinputembeddingsatthewhatoftheencoderanddecoderstacks.ĊĊOkay,ĠsoĠI'mĠtryingĠtoĠunderstand",
      "correct": false,
      "input_len": 1545,
      "compressed_len": 512,
      "retention_pct": 33.1,
      "prefill_time": 0.03080129623413086,
      "compress_time": 0.0057163238525390625,
      "decode_time": 0.927011251449585,
      "total_time": 1.0724611282348633,
      "peak_mem_gb": 15.912210464477539
    },
    {
      "section": "Training",
      "question": "What is the label smoothing value eps_ls used during training?",
      "expected": "0.1",
      "got": "0.1ĊĊOkay,ĠsoĠIĠneedĠtoĠfigureĠoutĠwhatĠtheĠlabelĠsmoothingĠvalueĠeps_lsĠisĠusedĠduringĠtraining.ĠI'mĠlookingĠthroughĠth",
      "correct": true,
      "input_len": 1536,
      "compressed_len": 512,
      "retention_pct": 33.3,
      "prefill_time": 0.02830219268798828,
      "compress_time": 0.005219697952270508,
      "decode_time": 0.8841042518615723,
      "total_time": 1.018932580947876,
      "peak_mem_gb": 15.908995628356934
    },
    {
      "section": "Results",
      "question": "How long did it take to train the big transformer model on 8 P100 GPUs?",
      "expected": "3.5 days|3.5days|3.5",
      "got": "Ittook3.5dayson8P100GPUs.ĊĊOkay,ĠsoĠIĠneedĠtoĠfigureĠoutĠhowĠlongĠitĠtookĠtoĠtrainĠtheĠbigĠtransformer",
      "correct": true,
      "input_len": 1542,
      "compressed_len": 512,
      "retention_pct": 33.2,
      "prefill_time": 0.030739307403564453,
      "compress_time": 0.0056726932525634766,
      "decode_time": 0.8912849426269531,
      "total_time": 1.0365550518035889,
      "peak_mem_gb": 15.911088943481445
    }
  ]
}